[{"family":"MaterialIcons","fonts":[{"asset":"fonts/MaterialIcons-Regular.ttf"}]},{"family":"SF-UI-Display-Regular","fonts":[{"asset":"assets/fonts/SF-UI-Display-Regular.otf"}]},{"family":"SF-UI-Display-Medium","fonts":[{"asset":"assets/fonts/SF-UI-Display-Medium.otf"}]},{"family":"SF-UI-Display-Semibold","fonts":[{"asset":"assets/fonts/SF-UI-Display-Semibold.otf"}]},{"family":"SF-UI-Display-Bold","fonts":[{"asset":"assets/fonts/SF-UI-Display-Bold.otf"}]},{"family":"SF-UI-Display-Black","fonts":[{"asset":"assets/fonts/SF-UI-Display-Black.otf"}]},{"family":"SF-UI-Display-Heavy","fonts":[{"asset":"assets/fonts/SF-UI-Display-Heavy.otf"}]},{"family":"SF-UI-Display-Light","fonts":[{"asset":"assets/fonts/SF-UI-Display-Light.otf"}]},{"family":"SF-UI-Display-Thin","fonts":[{"asset":"assets/fonts/SF-UI-Display-Thin.otf"}]},{"family":"SF-UI-Display-Ultralight","fonts":[{"asset":"assets/fonts/SF-UI-Display-Ultralight.otf"}]},{"family":"packages/cupertino_icons/CupertinoIcons","fonts":[{"asset":"packages/cupertino_icons/assets/CupertinoIcons.ttf"}]},{"family":"MaterialIcons","fonts":[{"asset":"fonts/MaterialIcons-Regular.ttf"}]}]